README.md
setup.cfg
setup.py
hamble/__init__.py
hamble/command.py
hamble/hamble.py
hamble.egg-info/PKG-INFO
hamble.egg-info/SOURCES.txt
hamble.egg-info/dependency_links.txt
hamble.egg-info/entry_points.txt
hamble.egg-info/requires.txt
hamble.egg-info/top_level.txt