Metadata-Version: 2.1
Name: hamble
Version: 0.0.5
Summary: Package for handling parameters from an ini file to configuration files.
Home-page: https://github.com/ndmikkelsen/hamble
Author: nathan mikkelsen
Author-email: nathan.mikkelsen@corteva.com
License: UNKNOWN
Platform: UNKNOWN
